syre/__about__.py
syre/__init__.py
syre/common.py
syre/database.py
syre/filter.py
syre/resources.py
syre/types.py
syre/bin/syre-project-daemon-x86_64-pc-windows-msvc.exe
syre-0.11.0.dist-info/METADATA
syre-0.11.0.dist-info/WHEEL
syre-0.11.0.dist-info/licenses/LICENSE-APACHE
syre-0.11.0.dist-info/licenses/LICENSE-MIT
syre-0.11.0.dist-info/RECORD
